{
  "schema_version": 1,
  "tolerance_percent": "5",
  "price_catalog_sha256": "935b70a56ebfd9adb46c33dfa57196d839a536c28657ed94ae6da23425aeca84",
  "checks": [
    {
      "source_row": 2,
      "source_position": "1",
      "estimate_work": "Окраска стен",
      "mcp_work_id": "wall_painting",
      "mcp_work_name": "Окраска стен",
      "unit": "м²",
      "estimate_price": "450",
      "mcp_price": "450",
      "quantity": "65.12",
      "estimate_total": "29304",
      "total_source": "provided_or_cached",
      "mcp_total": "29304",
      "price_deviation_absolute": "0",
      "price_deviation_percent": "0",
      "total_deviation_absolute": "0",
      "total_deviation_percent": "0",
      "unit_price_impact": "0",
      "unit_price_impact_formula": "(estimate_price - mcp_price) * estimate_quantity",
      "total_cost_impact": "0",
      "total_cost_impact_formula": "estimate_total - (estimate_quantity * mcp_price)",
      "deviation_absolute": "0",
      "deviation_percent": "0",
      "status": "checked",
      "reason": null
    },
    {
      "source_row": 3,
      "source_position": "2",
      "estimate_work": "Грунтовка стен",
      "mcp_work_id": "wall_priming",
      "mcp_work_name": "Грунтовка стен",
      "unit": "м²",
      "estimate_price": "120",
      "mcp_price": "120",
      "quantity": "65.12",
      "estimate_total": "7814.4",
      "total_source": "provided_or_cached",
      "mcp_total": "7814.4",
      "price_deviation_absolute": "0",
      "price_deviation_percent": "0",
      "total_deviation_absolute": "0",
      "total_deviation_percent": "0",
      "unit_price_impact": "0",
      "unit_price_impact_formula": "(estimate_price - mcp_price) * estimate_quantity",
      "total_cost_impact": "0",
      "total_cost_impact_formula": "estimate_total - (estimate_quantity * mcp_price)",
      "deviation_absolute": "0",
      "deviation_percent": "0",
      "status": "checked",
      "reason": null
    },
    {
      "source_row": 4,
      "source_position": "3",
      "estimate_work": "Устройство пола",
      "mcp_work_id": "floor_installation",
      "mcp_work_name": "Устройство пола",
      "unit": "м²",
      "estimate_price": "1700",
      "mcp_price": "1700",
      "quantity": "38.4",
      "estimate_total": "65280",
      "total_source": "provided_or_cached",
      "mcp_total": "65280",
      "price_deviation_absolute": "0",
      "price_deviation_percent": "0",
      "total_deviation_absolute": "0",
      "total_deviation_percent": "0",
      "unit_price_impact": "0",
      "unit_price_impact_formula": "(estimate_price - mcp_price) * estimate_quantity",
      "total_cost_impact": "0",
      "total_cost_impact_formula": "estimate_total - (estimate_quantity * mcp_price)",
      "deviation_absolute": "0",
      "deviation_percent": "0",
      "status": "checked",
      "reason": null
    },
    {
      "source_row": 5,
      "source_position": "4",
      "estimate_work": "Отделка потолка",
      "mcp_work_id": "ceiling_finishing",
      "mcp_work_name": "Отделка потолка",
      "unit": "м²",
      "estimate_price": "650",
      "mcp_price": "650",
      "quantity": "38.4",
      "estimate_total": "24960",
      "total_source": "provided_or_cached",
      "mcp_total": "24960",
      "price_deviation_absolute": "0",
      "price_deviation_percent": "0",
      "total_deviation_absolute": "0",
      "total_deviation_percent": "0",
      "unit_price_impact": "0",
      "unit_price_impact_formula": "(estimate_price - mcp_price) * estimate_quantity",
      "total_cost_impact": "0",
      "total_cost_impact_formula": "estimate_total - (estimate_quantity * mcp_price)",
      "deviation_absolute": "0",
      "deviation_percent": "0",
      "status": "checked",
      "reason": null
    },
    {
      "source_row": 6,
      "source_position": "5",
      "estimate_work": "Монтаж плинтуса",
      "mcp_work_id": "baseboard_installation",
      "mcp_work_name": "Монтаж плинтуса",
      "unit": "м",
      "estimate_price": "350",
      "mcp_price": "350",
      "quantity": "23.9",
      "estimate_total": "8365",
      "total_source": "provided_or_cached",
      "mcp_total": "8365",
      "price_deviation_absolute": "0",
      "price_deviation_percent": "0",
      "total_deviation_absolute": "0",
      "total_deviation_percent": "0",
      "unit_price_impact": "0",
      "unit_price_impact_formula": "(estimate_price - mcp_price) * estimate_quantity",
      "total_cost_impact": "0",
      "total_cost_impact_formula": "estimate_total - (estimate_quantity * mcp_price)",
      "deviation_absolute": "0",
      "deviation_percent": "0",
      "status": "checked",
      "reason": null
    },
    {
      "source_row": 7,
      "source_position": "6",
      "estimate_work": "Установка дверей",
      "mcp_work_id": "door_installation",
      "mcp_work_name": "Установка дверей",
      "unit": "шт.",
      "estimate_price": "7000",
      "mcp_price": "7000",
      "quantity": "1",
      "estimate_total": "7000",
      "total_source": "provided_or_cached",
      "mcp_total": "7000",
      "price_deviation_absolute": "0",
      "price_deviation_percent": "0",
      "total_deviation_absolute": "0",
      "total_deviation_percent": "0",
      "unit_price_impact": "0",
      "unit_price_impact_formula": "(estimate_price - mcp_price) * estimate_quantity",
      "total_cost_impact": "0",
      "total_cost_impact_formula": "estimate_total - (estimate_quantity * mcp_price)",
      "deviation_absolute": "0",
      "deviation_percent": "0",
      "status": "checked",
      "reason": null
    },
    {
      "source_row": 8,
      "source_position": "7",
      "estimate_work": "Установка окон",
      "mcp_work_id": "window_installation",
      "mcp_work_name": "Установка окон",
      "unit": "шт.",
      "estimate_price": "9000",
      "mcp_price": "9000",
      "quantity": "1",
      "estimate_total": "9000",
      "total_source": "provided_or_cached",
      "mcp_total": "9000",
      "price_deviation_absolute": "0",
      "price_deviation_percent": "0",
      "total_deviation_absolute": "0",
      "total_deviation_percent": "0",
      "unit_price_impact": "0",
      "unit_price_impact_formula": "(estimate_price - mcp_price) * estimate_quantity",
      "total_cost_impact": "0",
      "total_cost_impact_formula": "estimate_total - (estimate_quantity * mcp_price)",
      "deviation_absolute": "0",
      "deviation_percent": "0",
      "status": "checked",
      "reason": null
    },
    {
      "source_row": 9,
      "source_position": "8",
      "estimate_work": "Окраска стен",
      "mcp_work_id": "wall_painting",
      "mcp_work_name": "Окраска стен",
      "unit": "м²",
      "estimate_price": "450",
      "mcp_price": "450",
      "quantity": "54.24",
      "estimate_total": "24408",
      "total_source": "provided_or_cached",
      "mcp_total": "24408",
      "price_deviation_absolute": "0",
      "price_deviation_percent": "0",
      "total_deviation_absolute": "0",
      "total_deviation_percent": "0",
      "unit_price_impact": "0",
      "unit_price_impact_formula": "(estimate_price - mcp_price) * estimate_quantity",
      "total_cost_impact": "0",
      "total_cost_impact_formula": "estimate_total - (estimate_quantity * mcp_price)",
      "deviation_absolute": "0",
      "deviation_percent": "0",
      "status": "checked",
      "reason": null
    },
    {
      "source_row": 10,
      "source_position": "9",
      "estimate_work": "Грунтовка стен",
      "mcp_work_id": "wall_priming",
      "mcp_work_name": "Грунтовка стен",
      "unit": "м²",
      "estimate_price": "120",
      "mcp_price": "120",
      "quantity": "54.24",
      "estimate_total": "6508.8",
      "total_source": "provided_or_cached",
      "mcp_total": "6508.8",
      "price_deviation_absolute": "0",
      "price_deviation_percent": "0",
      "total_deviation_absolute": "0",
      "total_deviation_percent": "0",
      "unit_price_impact": "0",
      "unit_price_impact_formula": "(estimate_price - mcp_price) * estimate_quantity",
      "total_cost_impact": "0",
      "total_cost_impact_formula": "estimate_total - (estimate_quantity * mcp_price)",
      "deviation_absolute": "0",
      "deviation_percent": "0",
      "status": "checked",
      "reason": null
    },
    {
      "source_row": 11,
      "source_position": "10",
      "estimate_work": "Устройство пола",
      "mcp_work_id": "floor_installation",
      "mcp_work_name": "Устройство пола",
      "unit": "м²",
      "estimate_price": "1700",
      "mcp_price": "1700",
      "quantity": "30.6",
      "estimate_total": "52020",
      "total_source": "provided_or_cached",
      "mcp_total": "52020",
      "price_deviation_absolute": "0",
      "price_deviation_percent": "0",
      "total_deviation_absolute": "0",
      "total_deviation_percent": "0",
      "unit_price_impact": "0",
      "unit_price_impact_formula": "(estimate_price - mcp_price) * estimate_quantity",
      "total_cost_impact": "0",
      "total_cost_impact_formula": "estimate_total - (estimate_quantity * mcp_price)",
      "deviation_absolute": "0",
      "deviation_percent": "0",
      "status": "checked",
      "reason": null
    },
    {
      "source_row": 12,
      "source_position": "11",
      "estimate_work": "Отделка потолка",
      "mcp_work_id": "ceiling_finishing",
      "mcp_work_name": "Отделка потолка",
      "unit": "м²",
      "estimate_price": "650",
      "mcp_price": "650",
      "quantity": "30.6",
      "estimate_total": "19890",
      "total_source": "provided_or_cached",
      "mcp_total": "19890",
      "price_deviation_absolute": "0",
      "price_deviation_percent": "0",
      "total_deviation_absolute": "0",
      "total_deviation_percent": "0",
      "unit_price_impact": "0",
      "unit_price_impact_formula": "(estimate_price - mcp_price) * estimate_quantity",
      "total_cost_impact": "0",
      "total_cost_impact_formula": "estimate_total - (estimate_quantity * mcp_price)",
      "deviation_absolute": "0",
      "deviation_percent": "0",
      "status": "checked",
      "reason": null
    },
    {
      "source_row": 13,
      "source_position": "12",
      "estimate_work": "Монтаж плинтуса",
      "mcp_work_id": "baseboard_installation",
      "mcp_work_name": "Монтаж плинтуса",
      "unit": "м",
      "estimate_price": "350",
      "mcp_price": "350",
      "quantity": "19.5",
      "estimate_total": "6825",
      "total_source": "provided_or_cached",
      "mcp_total": "6825",
      "price_deviation_absolute": "0",
      "price_deviation_percent": "0",
      "total_deviation_absolute": "0",
      "total_deviation_percent": "0",
      "unit_price_impact": "0",
      "unit_price_impact_formula": "(estimate_price - mcp_price) * estimate_quantity",
      "total_cost_impact": "0",
      "total_cost_impact_formula": "estimate_total - (estimate_quantity * mcp_price)",
      "deviation_absolute": "0",
      "deviation_percent": "0",
      "status": "checked",
      "reason": null
    },
    {
      "source_row": 14,
      "source_position": "13",
      "estimate_work": "Установка дверей",
      "mcp_work_id": "door_installation",
      "mcp_work_name": "Установка дверей",
      "unit": "шт.",
      "estimate_price": "7000",
      "mcp_price": "7000",
      "quantity": "2",
      "estimate_total": "14000",
      "total_source": "provided_or_cached",
      "mcp_total": "14000",
      "price_deviation_absolute": "0",
      "price_deviation_percent": "0",
      "total_deviation_absolute": "0",
      "total_deviation_percent": "0",
      "unit_price_impact": "0",
      "unit_price_impact_formula": "(estimate_price - mcp_price) * estimate_quantity",
      "total_cost_impact": "0",
      "total_cost_impact_formula": "estimate_total - (estimate_quantity * mcp_price)",
      "deviation_absolute": "0",
      "deviation_percent": "0",
      "status": "checked",
      "reason": null
    },
    {
      "source_row": 15,
      "source_position": "14",
      "estimate_work": "Установка окон",
      "mcp_work_id": "window_installation",
      "mcp_work_name": "Установка окон",
      "unit": "шт.",
      "estimate_price": "9000",
      "mcp_price": "9000",
      "quantity": "1",
      "estimate_total": "9000",
      "total_source": "provided_or_cached",
      "mcp_total": "9000",
      "price_deviation_absolute": "0",
      "price_deviation_percent": "0",
      "total_deviation_absolute": "0",
      "total_deviation_percent": "0",
      "unit_price_impact": "0",
      "unit_price_impact_formula": "(estimate_price - mcp_price) * estimate_quantity",
      "total_cost_impact": "0",
      "total_cost_impact_formula": "estimate_total - (estimate_quantity * mcp_price)",
      "deviation_absolute": "0",
      "deviation_percent": "0",
      "status": "checked",
      "reason": null
    },
    {
      "source_row": 16,
      "source_position": "15",
      "estimate_work": "Окраска стен",
      "mcp_work_id": "wall_painting",
      "mcp_work_name": "Окраска стен",
      "unit": "м²",
      "estimate_price": "450",
      "mcp_price": "450",
      "quantity": "44.76",
      "estimate_total": "20142",
      "total_source": "provided_or_cached",
      "mcp_total": "20142",
      "price_deviation_absolute": "0",
      "price_deviation_percent": "0",
      "total_deviation_absolute": "0",
      "total_deviation_percent": "0",
      "unit_price_impact": "0",
      "unit_price_impact_formula": "(estimate_price - mcp_price) * estimate_quantity",
      "total_cost_impact": "0",
      "total_cost_impact_formula": "estimate_total - (estimate_quantity * mcp_price)",
      "deviation_absolute": "0",
      "deviation_percent": "0",
      "status": "checked",
      "reason": null
    },
    {
      "source_row": 17,
      "source_position": "16",
      "estimate_work": "Грунтовка стен",
      "mcp_work_id": "wall_priming",
      "mcp_work_name": "Грунтовка стен",
      "unit": "м²",
      "estimate_price": "120",
      "mcp_price": "120",
      "quantity": "44.76",
      "estimate_total": "5371.2",
      "total_source": "provided_or_cached",
      "mcp_total": "5371.2",
      "price_deviation_absolute": "0",
      "price_deviation_percent": "0",
      "total_deviation_absolute": "0",
      "total_deviation_percent": "0",
      "unit_price_impact": "0",
      "unit_price_impact_formula": "(estimate_price - mcp_price) * estimate_quantity",
      "total_cost_impact": "0",
      "total_cost_impact_formula": "estimate_total - (estimate_quantity * mcp_price)",
      "deviation_absolute": "0",
      "deviation_percent": "0",
      "status": "checked",
      "reason": null
    },
    {
      "source_row": 18,
      "source_position": "17",
      "estimate_work": "Устройство пола",
      "mcp_work_id": "floor_installation",
      "mcp_work_name": "Устройство пола",
      "unit": "м²",
      "estimate_price": "1700",
      "mcp_price": "1700",
      "quantity": "21.32",
      "estimate_total": "36244",
      "total_source": "provided_or_cached",
      "mcp_total": "36244",
      "price_deviation_absolute": "0",
      "price_deviation_percent": "0",
      "total_deviation_absolute": "0",
      "total_deviation_percent": "0",
      "unit_price_impact": "0",
      "unit_price_impact_formula": "(estimate_price - mcp_price) * estimate_quantity",
      "total_cost_impact": "0",
      "total_cost_impact_formula": "estimate_total - (estimate_quantity * mcp_price)",
      "deviation_absolute": "0",
      "deviation_percent": "0",
      "status": "checked",
      "reason": null
    },
    {
      "source_row": 19,
      "source_position": "18",
      "estimate_work": "Отделка потолка",
      "mcp_work_id": "ceiling_finishing",
      "mcp_work_name": "Отделка потолка",
      "unit": "м²",
      "estimate_price": "650",
      "mcp_price": "650",
      "quantity": "21.32",
      "estimate_total": "13858",
      "total_source": "provided_or_cached",
      "mcp_total": "13858",
      "price_deviation_absolute": "0",
      "price_deviation_percent": "0",
      "total_deviation_absolute": "0",
      "total_deviation_percent": "0",
      "unit_price_impact": "0",
      "unit_price_impact_formula": "(estimate_price - mcp_price) * estimate_quantity",
      "total_cost_impact": "0",
      "total_cost_impact_formula": "estimate_total - (estimate_quantity * mcp_price)",
      "deviation_absolute": "0",
      "deviation_percent": "0",
      "status": "checked",
      "reason": null
    },
    {
      "source_row": 20,
      "source_position": "19",
      "estimate_work": "Монтаж плинтуса",
      "mcp_work_id": "baseboard_installation",
      "mcp_work_name": "Монтаж плинтуса",
      "unit": "м",
      "estimate_price": "350",
      "mcp_price": "350",
      "quantity": "16.2",
      "estimate_total": "5670",
      "total_source": "provided_or_cached",
      "mcp_total": "5670",
      "price_deviation_absolute": "0",
      "price_deviation_percent": "0",
      "total_deviation_absolute": "0",
      "total_deviation_percent": "0",
      "unit_price_impact": "0",
      "unit_price_impact_formula": "(estimate_price - mcp_price) * estimate_quantity",
      "total_cost_impact": "0",
      "total_cost_impact_formula": "estimate_total - (estimate_quantity * mcp_price)",
      "deviation_absolute": "0",
      "deviation_percent": "0",
      "status": "checked",
      "reason": null
    },
    {
      "source_row": 21,
      "source_position": "20",
      "estimate_work": "Установка дверей",
      "mcp_work_id": "door_installation",
      "mcp_work_name": "Установка дверей",
      "unit": "шт.",
      "estimate_price": "7000",
      "mcp_price": "7000",
      "quantity": "1",
      "estimate_total": "7000",
      "total_source": "provided_or_cached",
      "mcp_total": "7000",
      "price_deviation_absolute": "0",
      "price_deviation_percent": "0",
      "total_deviation_absolute": "0",
      "total_deviation_percent": "0",
      "unit_price_impact": "0",
      "unit_price_impact_formula": "(estimate_price - mcp_price) * estimate_quantity",
      "total_cost_impact": "0",
      "total_cost_impact_formula": "estimate_total - (estimate_quantity * mcp_price)",
      "deviation_absolute": "0",
      "deviation_percent": "0",
      "status": "checked",
      "reason": null
    },
    {
      "source_row": 22,
      "source_position": "21",
      "estimate_work": "Установка окон",
      "mcp_work_id": "window_installation",
      "mcp_work_name": "Установка окон",
      "unit": "шт.",
      "estimate_price": "9000",
      "mcp_price": "9000",
      "quantity": "1",
      "estimate_total": "9000",
      "total_source": "provided_or_cached",
      "mcp_total": "9000",
      "price_deviation_absolute": "0",
      "price_deviation_percent": "0",
      "total_deviation_absolute": "0",
      "total_deviation_percent": "0",
      "unit_price_impact": "0",
      "unit_price_impact_formula": "(estimate_price - mcp_price) * estimate_quantity",
      "total_cost_impact": "0",
      "total_cost_impact_formula": "estimate_total - (estimate_quantity * mcp_price)",
      "deviation_absolute": "0",
      "deviation_percent": "0",
      "status": "checked",
      "reason": null
    },
    {
      "source_row": 23,
      "source_position": "22",
      "estimate_work": "Окраска стен",
      "mcp_work_id": "wall_painting",
      "mcp_work_name": "Окраска стен",
      "unit": "м²",
      "estimate_price": "450",
      "mcp_price": "450",
      "quantity": "45.4",
      "estimate_total": "20430",
      "total_source": "provided_or_cached",
      "mcp_total": "20430",
      "price_deviation_absolute": "0",
      "price_deviation_percent": "0",
      "total_deviation_absolute": "0",
      "total_deviation_percent": "0",
      "unit_price_impact": "0",
      "unit_price_impact_formula": "(estimate_price - mcp_price) * estimate_quantity",
      "total_cost_impact": "0",
      "total_cost_impact_formula": "estimate_total - (estimate_quantity * mcp_price)",
      "deviation_absolute": "0",
      "deviation_percent": "0",
      "status": "checked",
      "reason": null
    },
    {
      "source_row": 24,
      "source_position": "23",
      "estimate_work": "Грунтовка стен",
      "mcp_work_id": "wall_priming",
      "mcp_work_name": "Грунтовка стен",
      "unit": "м²",
      "estimate_price": "120",
      "mcp_price": "120",
      "quantity": "45.4",
      "estimate_total": "5448",
      "total_source": "provided_or_cached",
      "mcp_total": "5448",
      "price_deviation_absolute": "0",
      "price_deviation_percent": "0",
      "total_deviation_absolute": "0",
      "total_deviation_percent": "0",
      "unit_price_impact": "0",
      "unit_price_impact_formula": "(estimate_price - mcp_price) * estimate_quantity",
      "total_cost_impact": "0",
      "total_cost_impact_formula": "estimate_total - (estimate_quantity * mcp_price)",
      "deviation_absolute": "0",
      "deviation_percent": "0",
      "status": "checked",
      "reason": null
    },
    {
      "source_row": 25,
      "source_position": "24",
      "estimate_work": "Устройство пола",
      "mcp_work_id": "floor_installation",
      "mcp_work_name": "Устройство пола",
      "unit": "м²",
      "estimate_price": "1700",
      "mcp_price": "1700",
      "quantity": "18.6",
      "estimate_total": "31620",
      "total_source": "provided_or_cached",
      "mcp_total": "31620",
      "price_deviation_absolute": "0",
      "price_deviation_percent": "0",
      "total_deviation_absolute": "0",
      "total_deviation_percent": "0",
      "unit_price_impact": "0",
      "unit_price_impact_formula": "(estimate_price - mcp_price) * estimate_quantity",
      "total_cost_impact": "0",
      "total_cost_impact_formula": "estimate_total - (estimate_quantity * mcp_price)",
      "deviation_absolute": "0",
      "deviation_percent": "0",
      "status": "checked",
      "reason": null
    },
    {
      "source_row": 26,
      "source_position": "25",
      "estimate_work": "Отделка потолка",
      "mcp_work_id": "ceiling_finishing",
      "mcp_work_name": "Отделка потолка",
      "unit": "м²",
      "estimate_price": "650",
      "mcp_price": "650",
      "quantity": "18.6",
      "estimate_total": "12090",
      "total_source": "provided_or_cached",
      "mcp_total": "12090",
      "price_deviation_absolute": "0",
      "price_deviation_percent": "0",
      "total_deviation_absolute": "0",
      "total_deviation_percent": "0",
      "unit_price_impact": "0",
      "unit_price_impact_formula": "(estimate_price - mcp_price) * estimate_quantity",
      "total_cost_impact": "0",
      "total_cost_impact_formula": "estimate_total - (estimate_quantity * mcp_price)",
      "deviation_absolute": "0",
      "deviation_percent": "0",
      "status": "checked",
      "reason": null
    },
    {
      "source_row": 27,
      "source_position": "26",
      "estimate_work": "Монтаж плинтуса",
      "mcp_work_id": "baseboard_installation",
      "mcp_work_name": "Монтаж плинтуса",
      "unit": "м",
      "estimate_price": "350",
      "mcp_price": "350",
      "quantity": "16.4",
      "estimate_total": "5740",
      "total_source": "provided_or_cached",
      "mcp_total": "5740",
      "price_deviation_absolute": "0",
      "price_deviation_percent": "0",
      "total_deviation_absolute": "0",
      "total_deviation_percent": "0",
      "unit_price_impact": "0",
      "unit_price_impact_formula": "(estimate_price - mcp_price) * estimate_quantity",
      "total_cost_impact": "0",
      "total_cost_impact_formula": "estimate_total - (estimate_quantity * mcp_price)",
      "deviation_absolute": "0",
      "deviation_percent": "0",
      "status": "checked",
      "reason": null
    },
    {
      "source_row": 28,
      "source_position": "27",
      "estimate_work": "Установка дверей",
      "mcp_work_id": "door_installation",
      "mcp_work_name": "Установка дверей",
      "unit": "шт.",
      "estimate_price": "7000",
      "mcp_price": "7000",
      "quantity": "1",
      "estimate_total": "7000",
      "total_source": "provided_or_cached",
      "mcp_total": "7000",
      "price_deviation_absolute": "0",
      "price_deviation_percent": "0",
      "total_deviation_absolute": "0",
      "total_deviation_percent": "0",
      "unit_price_impact": "0",
      "unit_price_impact_formula": "(estimate_price - mcp_price) * estimate_quantity",
      "total_cost_impact": "0",
      "total_cost_impact_formula": "estimate_total - (estimate_quantity * mcp_price)",
      "deviation_absolute": "0",
      "deviation_percent": "0",
      "status": "checked",
      "reason": null
    },
    {
      "source_row": 29,
      "source_position": "28",
      "estimate_work": "Установка окон",
      "mcp_work_id": "window_installation",
      "mcp_work_name": "Установка окон",
      "unit": "шт.",
      "estimate_price": "9000",
      "mcp_price": "9000",
      "quantity": "1",
      "estimate_total": "9000",
      "total_source": "provided_or_cached",
      "mcp_total": "9000",
      "price_deviation_absolute": "0",
      "price_deviation_percent": "0",
      "total_deviation_absolute": "0",
      "total_deviation_percent": "0",
      "unit_price_impact": "0",
      "unit_price_impact_formula": "(estimate_price - mcp_price) * estimate_quantity",
      "total_cost_impact": "0",
      "total_cost_impact_formula": "estimate_total - (estimate_quantity * mcp_price)",
      "deviation_absolute": "0",
      "deviation_percent": "0",
      "status": "checked",
      "reason": null
    },
    {
      "source_row": 30,
      "source_position": "29",
      "estimate_work": "Окраска стен",
      "mcp_work_id": "wall_painting",
      "mcp_work_name": "Окраска стен",
      "unit": "м²",
      "estimate_price": "450",
      "mcp_price": "450",
      "quantity": "30.64",
      "estimate_total": "13788",
      "total_source": "provided_or_cached",
      "mcp_total": "13788",
      "price_deviation_absolute": "0",
      "price_deviation_percent": "0",
      "total_deviation_absolute": "0",
      "total_deviation_percent": "0",
      "unit_price_impact": "0",
      "unit_price_impact_formula": "(estimate_price - mcp_price) * estimate_quantity",
      "total_cost_impact": "0",
      "total_cost_impact_formula": "estimate_total - (estimate_quantity * mcp_price)",
      "deviation_absolute": "0",
      "deviation_percent": "0",
      "status": "checked",
      "reason": null
    },
    {
      "source_row": 31,
      "source_position": "30",
      "estimate_work": "Грунтовка стен",
      "mcp_work_id": "wall_priming",
      "mcp_work_name": "Грунтовка стен",
      "unit": "м²",
      "estimate_price": "120",
      "mcp_price": "120",
      "quantity": "30.64",
      "estimate_total": "3676.8",
      "total_source": "provided_or_cached",
      "mcp_total": "3676.8",
      "price_deviation_absolute": "0",
      "price_deviation_percent": "0",
      "total_deviation_absolute": "0",
      "total_deviation_percent": "0",
      "unit_price_impact": "0",
      "unit_price_impact_formula": "(estimate_price - mcp_price) * estimate_quantity",
      "total_cost_impact": "0",
      "total_cost_impact_formula": "estimate_total - (estimate_quantity * mcp_price)",
      "deviation_absolute": "0",
      "deviation_percent": "0",
      "status": "checked",
      "reason": null
    },
    {
      "source_row": 32,
      "source_position": "31",
      "estimate_work": "Устройство пола",
      "mcp_work_id": "floor_installation",
      "mcp_work_name": "Устройство пола",
      "unit": "м²",
      "estimate_price": "1700",
      "mcp_price": "1700",
      "quantity": "10.8",
      "estimate_total": "18360",
      "total_source": "provided_or_cached",
      "mcp_total": "18360",
      "price_deviation_absolute": "0",
      "price_deviation_percent": "0",
      "total_deviation_absolute": "0",
      "total_deviation_percent": "0",
      "unit_price_impact": "0",
      "unit_price_impact_formula": "(estimate_price - mcp_price) * estimate_quantity",
      "total_cost_impact": "0",
      "total_cost_impact_formula": "estimate_total - (estimate_quantity * mcp_price)",
      "deviation_absolute": "0",
      "deviation_percent": "0",
      "status": "checked",
      "reason": null
    },
    {
      "source_row": 33,
      "source_position": "32",
      "estimate_work": "Отделка потолка",
      "mcp_work_id": "ceiling_finishing",
      "mcp_work_name": "Отделка потолка",
      "unit": "м²",
      "estimate_price": "650",
      "mcp_price": "650",
      "quantity": "10.8",
      "estimate_total": "7020",
      "total_source": "provided_or_cached",
      "mcp_total": "7020",
      "price_deviation_absolute": "0",
      "price_deviation_percent": "0",
      "total_deviation_absolute": "0",
      "total_deviation_percent": "0",
      "unit_price_impact": "0",
      "unit_price_impact_formula": "(estimate_price - mcp_price) * estimate_quantity",
      "total_cost_impact": "0",
      "total_cost_impact_formula": "estimate_total - (estimate_quantity * mcp_price)",
      "deviation_absolute": "0",
      "deviation_percent": "0",
      "status": "checked",
      "reason": null
    },
    {
      "source_row": 34,
      "source_position": "33",
      "estimate_work": "Монтаж плинтуса",
      "mcp_work_id": "baseboard_installation",
      "mcp_work_name": "Монтаж плинтуса",
      "unit": "м",
      "estimate_price": "350",
      "mcp_price": "350",
      "quantity": "10.8",
      "estimate_total": "3780",
      "total_source": "provided_or_cached",
      "mcp_total": "3780",
      "price_deviation_absolute": "0",
      "price_deviation_percent": "0",
      "total_deviation_absolute": "0",
      "total_deviation_percent": "0",
      "unit_price_impact": "0",
      "unit_price_impact_formula": "(estimate_price - mcp_price) * estimate_quantity",
      "total_cost_impact": "0",
      "total_cost_impact_formula": "estimate_total - (estimate_quantity * mcp_price)",
      "deviation_absolute": "0",
      "deviation_percent": "0",
      "status": "checked",
      "reason": null
    },
    {
      "source_row": 35,
      "source_position": "34",
      "estimate_work": "Установка дверей",
      "mcp_work_id": "door_installation",
      "mcp_work_name": "Установка дверей",
      "unit": "шт.",
      "estimate_price": "7000",
      "mcp_price": "7000",
      "quantity": "1",
      "estimate_total": "7000",
      "total_source": "provided_or_cached",
      "mcp_total": "7000",
      "price_deviation_absolute": "0",
      "price_deviation_percent": "0",
      "total_deviation_absolute": "0",
      "total_deviation_percent": "0",
      "unit_price_impact": "0",
      "unit_price_impact_formula": "(estimate_price - mcp_price) * estimate_quantity",
      "total_cost_impact": "0",
      "total_cost_impact_formula": "estimate_total - (estimate_quantity * mcp_price)",
      "deviation_absolute": "0",
      "deviation_percent": "0",
      "status": "checked",
      "reason": null
    },
    {
      "source_row": 36,
      "source_position": "35",
      "estimate_work": "Установка окон",
      "mcp_work_id": "window_installation",
      "mcp_work_name": "Установка окон",
      "unit": "шт.",
      "estimate_price": "9000",
      "mcp_price": "9000",
      "quantity": "1",
      "estimate_total": "9000",
      "total_source": "provided_or_cached",
      "mcp_total": "9000",
      "price_deviation_absolute": "0",
      "price_deviation_percent": "0",
      "total_deviation_absolute": "0",
      "total_deviation_percent": "0",
      "unit_price_impact": "0",
      "unit_price_impact_formula": "(estimate_price - mcp_price) * estimate_quantity",
      "total_cost_impact": "0",
      "total_cost_impact_formula": "estimate_total - (estimate_quantity * mcp_price)",
      "deviation_absolute": "0",
      "deviation_percent": "0",
      "status": "checked",
      "reason": null
    },
    {
      "source_row": 37,
      "source_position": "36",
      "estimate_work": "Окраска стен",
      "mcp_work_id": "wall_painting",
      "mcp_work_name": "Окраска стен",
      "unit": "м²",
      "estimate_price": "450",
      "mcp_price": "450",
      "quantity": "30.54",
      "estimate_total": "13743",
      "total_source": "provided_or_cached",
      "mcp_total": "13743",
      "price_deviation_absolute": "0",
      "price_deviation_percent": "0",
      "total_deviation_absolute": "0",
      "total_deviation_percent": "0",
      "unit_price_impact": "0",
      "unit_price_impact_formula": "(estimate_price - mcp_price) * estimate_quantity",
      "total_cost_impact": "0",
      "total_cost_impact_formula": "estimate_total - (estimate_quantity * mcp_price)",
      "deviation_absolute": "0",
      "deviation_percent": "0",
      "status": "checked",
      "reason": null
    },
    {
      "source_row": 38,
      "source_position": "37",
      "estimate_work": "Грунтовка стен",
      "mcp_work_id": "wall_priming",
      "mcp_work_name": "Грунтовка стен",
      "unit": "м²",
      "estimate_price": "120",
      "mcp_price": "120",
      "quantity": "30.54",
      "estimate_total": "3664.8",
      "total_source": "provided_or_cached",
      "mcp_total": "3664.8",
      "price_deviation_absolute": "0",
      "price_deviation_percent": "0",
      "total_deviation_absolute": "0",
      "total_deviation_percent": "0",
      "unit_price_impact": "0",
      "unit_price_impact_formula": "(estimate_price - mcp_price) * estimate_quantity",
      "total_cost_impact": "0",
      "total_cost_impact_formula": "estimate_total - (estimate_quantity * mcp_price)",
      "deviation_absolute": "0",
      "deviation_percent": "0",
      "status": "checked",
      "reason": null
    },
    {
      "source_row": 39,
      "source_position": "38",
      "estimate_work": "Устройство пола",
      "mcp_work_id": "floor_installation",
      "mcp_work_name": "Устройство пола",
      "unit": "м²",
      "estimate_price": "1700",
      "mcp_price": "1700",
      "quantity": "9.2",
      "estimate_total": "15640",
      "total_source": "provided_or_cached",
      "mcp_total": "15640",
      "price_deviation_absolute": "0",
      "price_deviation_percent": "0",
      "total_deviation_absolute": "0",
      "total_deviation_percent": "0",
      "unit_price_impact": "0",
      "unit_price_impact_formula": "(estimate_price - mcp_price) * estimate_quantity",
      "total_cost_impact": "0",
      "total_cost_impact_formula": "estimate_total - (estimate_quantity * mcp_price)",
      "deviation_absolute": "0",
      "deviation_percent": "0",
      "status": "checked",
      "reason": null
    },
    {
      "source_row": 40,
      "source_position": "39",
      "estimate_work": "Отделка потолка",
      "mcp_work_id": "ceiling_finishing",
      "mcp_work_name": "Отделка потолка",
      "unit": "м²",
      "estimate_price": "650",
      "mcp_price": "650",
      "quantity": "9.2",
      "estimate_total": "5980",
      "total_source": "provided_or_cached",
      "mcp_total": "5980",
      "price_deviation_absolute": "0",
      "price_deviation_percent": "0",
      "total_deviation_absolute": "0",
      "total_deviation_percent": "0",
      "unit_price_impact": "0",
      "unit_price_impact_formula": "(estimate_price - mcp_price) * estimate_quantity",
      "total_cost_impact": "0",
      "total_cost_impact_formula": "estimate_total - (estimate_quantity * mcp_price)",
      "deviation_absolute": "0",
      "deviation_percent": "0",
      "status": "checked",
      "reason": null
    },
    {
      "source_row": 41,
      "source_position": "40",
      "estimate_work": "Монтаж плинтуса",
      "mcp_work_id": "baseboard_installation",
      "mcp_work_name": "Монтаж плинтуса",
      "unit": "м",
      "estimate_price": "350",
      "mcp_price": "350",
      "quantity": "11",
      "estimate_total": "3850",
      "total_source": "provided_or_cached",
      "mcp_total": "3850",
      "price_deviation_absolute": "0",
      "price_deviation_percent": "0",
      "total_deviation_absolute": "0",
      "total_deviation_percent": "0",
      "unit_price_impact": "0",
      "unit_price_impact_formula": "(estimate_price - mcp_price) * estimate_quantity",
      "total_cost_impact": "0",
      "total_cost_impact_formula": "estimate_total - (estimate_quantity * mcp_price)",
      "deviation_absolute": "0",
      "deviation_percent": "0",
      "status": "checked",
      "reason": null
    },
    {
      "source_row": 42,
      "source_position": "41",
      "estimate_work": "Установка дверей",
      "mcp_work_id": "door_installation",
      "mcp_work_name": "Установка дверей",
      "unit": "шт.",
      "estimate_price": "7000",
      "mcp_price": "7000",
      "quantity": "1",
      "estimate_total": "7000",
      "total_source": "provided_or_cached",
      "mcp_total": "7000",
      "price_deviation_absolute": "0",
      "price_deviation_percent": "0",
      "total_deviation_absolute": "0",
      "total_deviation_percent": "0",
      "unit_price_impact": "0",
      "unit_price_impact_formula": "(estimate_price - mcp_price) * estimate_quantity",
      "total_cost_impact": "0",
      "total_cost_impact_formula": "estimate_total - (estimate_quantity * mcp_price)",
      "deviation_absolute": "0",
      "deviation_percent": "0",
      "status": "checked",
      "reason": null
    },
    {
      "source_row": 43,
      "source_position": "42",
      "estimate_work": "Установка окон",
      "mcp_work_id": "window_installation",
      "mcp_work_name": "Установка окон",
      "unit": "шт.",
      "estimate_price": "9000",
      "mcp_price": "9000",
      "quantity": "1",
      "estimate_total": "9000",
      "total_source": "provided_or_cached",
      "mcp_total": "9000",
      "price_deviation_absolute": "0",
      "price_deviation_percent": "0",
      "total_deviation_absolute": "0",
      "total_deviation_percent": "0",
      "unit_price_impact": "0",
      "unit_price_impact_formula": "(estimate_price - mcp_price) * estimate_quantity",
      "total_cost_impact": "0",
      "total_cost_impact_formula": "estimate_total - (estimate_quantity * mcp_price)",
      "deviation_absolute": "0",
      "deviation_percent": "0",
      "status": "checked",
      "reason": null
    }
  ]
}
